nkmodel/__init__.py
nkmodel/nk.py
nkmodel-0.0.6.dist-info/LICENSE
nkmodel-0.0.6.dist-info/METADATA
nkmodel-0.0.6.dist-info/WHEEL
nkmodel-0.0.6.dist-info/top_level.txt
nkmodel-0.0.6.dist-info/RECORD
