Metadata-Version: 2.1
Name: nkmodel
Version: 0.0.6
Summary: Implementation of Kauffman NK Model
Home-page: https://github.com/elplatt/nkmodel
Author: Edward L Platt
Author-email: ed@elplatt.com
License: UNKNOWN
Platform: UNKNOWN
Classifier: Programming Language :: Python :: 3
Classifier: License :: OSI Approved :: BSD License
Classifier: Operating System :: OS Independent
Requires-Python: >=3.6
